[
  {
    "title": "title1",
    "description": "description1",
    "likes": "2",
    "url": "https://picsum.photos/100"
  },
  {
    "title": "title2",
    "description": "description2",
    "likes": "2",
    "url": "https://picsum.photos/101"
  },
  {
    "title": "title3",
    "description": "description3",

    "likes": "9",
    "url": "https://picsum.photos/102"
  },
  {
    "title": "title4",
    "description": "description4",
    "likes": "4",
    "url": "https://picsum.photos/103"
  },
  {
    "title": "title5",
    "description": "description5",
    "likes": "6",
    "url": "https://picsum.photos/104"
  },
  {
    "title": "title6",
    "description": "description6",
    "likes": "5",
    "url": "https://picsum.photos/105"
  },
  {
    "title": "title7",
    "description": "description7",
    "likes": "7",
    "url": "https://picsum.photos/106"
  },
  {
    "title": "title8",
    "description": "description8",
    "likes": "1",
    "url": "https://picsum.photos/107"
  },
  {
    "title": "title9",
    "description": "description9",
    "likes": "5",
    "url": "https://picsum.photos/108"
  },
  {
    "title": "title10",
    "description": "description10",
    "likes": "7",
    "url": "https://picsum.photos/109"
  },
  {
    "title": "title11",
    "description": "description11",
    "likes": "5",
    "url": "https://picsum.photos/110"
  },
  {
    "title": "title12",
    "description": "description12",
    "likes": "4",
    "url": "https://picsum.photos/111"
  },
  {
    "title": "title13",
    "description": "description13",

    "likes": "2",
    "url": "https://picsum.photos/112",
    "": "13"
  },
  {
    "title": "title14",
    "description": "description14",

    "likes": "4",
    "url": "https://picsum.photos/113",
    "": "14"
  },
  {
    "title": "title15",
    "description": "description15",
    "likes": "2",
    "url": "https://picsum.photos/114"
  },
  {
    "title": "title16",
    "description": "description16",
    "likes": "6",
    "url": "https://picsum.photos/115"
  },
  {
    "title": "title17",
    "description": "description17",
    "likes": "9",
    "url": "https://picsum.photos/116"
  },
  {
    "title": "title18",
    "description": "description18",
    "likes": "8",
    "url": "https://picsum.photos/117"
  },
  {
    "title": "title19",
    "description": "description19",
    "likes": "9",
    "url": "https://picsum.photos/118"
  }
]
